swarm/__init__.py
swarm/core.py
swarm/types.py
swarm/util.py
agentstack_openai_swarm-0.0.1.dist-info/LICENSE
agentstack_openai_swarm-0.0.1.dist-info/METADATA
agentstack_openai_swarm-0.0.1.dist-info/WHEEL
agentstack_openai_swarm-0.0.1.dist-info/top_level.txt
agentstack_openai_swarm-0.0.1.dist-info/zip-safe
agentstack_openai_swarm-0.0.1.dist-info/RECORD
