Metadata-Version: 2.2
Name: agentstack-openai-swarm
Version: 0.0.1
Summary: Forked version of OpenAI's Swarm library
Author: OpenAI Solutions
Author-email: Braelyn Boynton <bboynton97@gmail.com>
License: MIT
Project-URL: Homepage, https://github.com/yourusername/agentstack-openai-swarm
Project-URL: Repository, https://github.com/yourusername/agentstack-openai-swarm
Requires-Python: >=3.7
License-File: LICENSE
